maidwhite/MaidWhite.py
maidwhite/__init__.py
maidwhite-0.0.1.dist-info/LICENSE
maidwhite-0.0.1.dist-info/METADATA
maidwhite-0.0.1.dist-info/WHEEL
maidwhite-0.0.1.dist-info/top_level.txt
maidwhite-0.0.1.dist-info/RECORD
