Metadata-Version: 2.1
Name: maidwhite
Version: 0.0.1
Summary: Maid White SDK in Python
Home-page: https://github.com/tihtw/maidwhite-python
Author: Pichu Chen
Author-email: pichu@tih.tw
License: UNKNOWN
Platform: UNKNOWN
Classifier: Programming Language :: Python :: 3
Classifier: License :: OSI Approved :: Apache Software License
Classifier: Operating System :: OS Independent
